rompy/__init__.py
rompy/_version.py
rompy/cli.py
rompy/formatting.py
rompy/model.py
rompy/plotting.py
rompy/utils.py
rompy/backends/__init__.py
rompy/backends/config.py
rompy/core/__init__.py
rompy/core/boundary.py
rompy/core/config.py
rompy/core/data.py
rompy/core/filters.py
rompy/core/grid.py
rompy/core/render.py
rompy/core/source.py
rompy/core/spectrum.py
rompy/core/time.py
rompy/core/types.py
rompy/logging/__init__.py
rompy/logging/config.py
rompy/logging/formatter.py
rompy/logging/logger.py
rompy/pipeline/__init__.py
rompy/postprocess/__init__.py
rompy/run/__init__.py
rompy/run/docker.py
rompy/templates/base/__init__.py
rompy/templates/base/{{runtime.staging_dir}}/INPUT
rompy/templates/base/{{runtime.staging_dir}}/datasets/readme.md
rompy/templates/base/{{runtime.staging_dir}}/outputs/readme.md
rompy-0.6.1.dist-info/licenses/AUTHORS.rst
rompy-0.6.1.dist-info/licenses/LICENSE
rompy-0.6.1.dist-info/licenses/NOTICE
rompy-0.6.1.dist-info/METADATA
rompy-0.6.1.dist-info/WHEEL
rompy-0.6.1.dist-info/entry_points.txt
rompy-0.6.1.dist-info/top_level.txt
rompy-0.6.1.dist-info/RECORD
