Metadata-Version: 2.4
Name: rompy
Version: 0.6.1
Summary: Core rompy library for ocean wave modeling with plugin system
Author-email: CSIRO <paul.branson@csiro.au>
Maintainer-email: Rompy Contributors <developers@rompy.com>
License: 
Project-URL: Documentation, https://oceanum.github.io/rompy/index.html
Project-URL: Source, https://github.com/rom-py/rompy
Project-URL: Tracker, https://github.com/rom-py/rompy/issues
Project-URL: Changelog, https://github.com/rom-py/rompy/blob/main/HISTORY.rst
Keywords: relocatable,ocean,modelling,python,csiro
Classifier: Development Status :: 3 - Alpha
Classifier: Intended Audience :: Science/Research
Classifier: License :: OSI Approved :: Apache Software License
Classifier: Natural Language :: English
Classifier: Operating System :: OS Independent
Classifier: Topic :: Scientific/Engineering
Classifier: Topic :: Scientific/Engineering :: Physics
Classifier: Topic :: Scientific/Engineering :: Visualization
Classifier: Programming Language :: Python :: 3
Classifier: Programming Language :: Python :: 3.10
Classifier: Programming Language :: Python :: 3.11
Classifier: Programming Language :: Python :: 3.12
Requires-Python: >=3.10
License-File: LICENSE
License-File: NOTICE
License-File: AUTHORS.rst
Requires-Dist: cartopy
Requires-Dist: click
Requires-Dist: cloudpathlib
Requires-Dist: cookiecutter>=2.6
Requires-Dist: dask
Requires-Dist: fsspec
Requires-Dist: geopandas
Requires-Dist: h5py
Requires-Dist: intake
Requires-Dist: intake-xarray
Requires-Dist: intake-geopandas
Requires-Dist: matplotlib
Requires-Dist: netcdf4
Requires-Dist: numpy
Requires-Dist: oceanum
Requires-Dist: owslib
Requires-Dist: pandas
Requires-Dist: pydantic>2
Requires-Dist: pydantic-settings
Requires-Dist: pydantic_numpy
Requires-Dist: scipy
Requires-Dist: tqdm
Requires-Dist: xarray
Requires-Dist: wavespectra
Requires-Dist: isodate
Requires-Dist: appdirs
Provides-Extra: test
Requires-Dist: pytest; extra == "test"
Requires-Dist: envyaml; extra == "test"
Requires-Dist: coverage; extra == "test"
Provides-Extra: extra
Requires-Dist: gcsfs; extra == "extra"
Requires-Dist: zarr; extra == "extra"
Provides-Extra: dev
Requires-Dist: pytest; extra == "dev"
Requires-Dist: envyaml; extra == "dev"
Requires-Dist: coverage; extra == "dev"
Requires-Dist: ruff; extra == "dev"
Requires-Dist: black; extra == "dev"
Provides-Extra: docs
Requires-Dist: autodoc_pydantic; extra == "docs"
Requires-Dist: ipython; extra == "docs"
Requires-Dist: nbsphinx; extra == "docs"
Requires-Dist: pydata_sphinx_theme; extra == "docs"
Requires-Dist: sphinx<7.3.6; extra == "docs"
Requires-Dist: sphinx-collections; extra == "docs"
Dynamic: license-file
